Tutorial/ha.vhdl
library ieee;
use ieee.std_logic_1164.all;

entity ha is
    port (a, b : in std_logic; s, c : out std_logic);
end ha;

architecture basic of ha is
begin
    s <= a xor b;
    c <= a and b;
end architecture basic;

Tutorial/fa.vhdl
library ieee;
use ieee.std_logic_1164.all;

entity fa is
    port (a, b, ci : in std_logic; s, co : out std_logic);
end fa;

architecture basic of fa is
    signal s0, s1, c0, c1 : std_logic; -- temps for connecting outputs to inputs
begin
    ha0: entity work.ha port map (a, b, s0, c0);
    ha1: entity work.ha port map (s0, ci, s1, c1);
    s <= s1;
    co <= c0 or c1;
end architecture basic;

Tutorial/RippleCarryAdder.vhdl
library ieee;
use ieee.std_logic_1164.all;

entity RippleCarryAdder is
    port (a, b : in std_logic_vector(2 downto 0); s : out std_logic_vector(3 downto 0));
end RippleCarryAdder;

architecture basic of RippleCarryAdder is
signal c0, c1 : std_logic;
begin
    ha: entity work.ha port map(a(0), b(0), s(0), c0);
    fa0: entity work.fa port map (a(1), b(1), c0, s(1), c1);
    fa1: entity work.fa port map (a(2), b(2), c1, s(2), s(3));
end architecture basic;

Tutorial/CarrySaveAdder.vhdl
library ieee;
use ieee.std_logic_1164.all;

entity CarrySaveAdder is
    port(a, b, c, d : in std_logic_vector(2 downto 0); s : out std_logic_vector(4 downto 0));
end CarrySaveAdder;

architecture basic of CarrySaveAdder is
signal fls, flc: std_logic_vector(2 downto 0);
signal sls: std_logic_vector(1 downto 0);
signal slc: std_logic_vector(2 downto 0);
signal rcai1: std_logic_vector(2 downto 0);
begin
    csa0: entity work.fa port map (a(0), b(0), c(0), fls(0), flc(0));
    csa1: entity work.fa port map (a(1), b(1), c(1), fls(1), flc(1));
    csa2: entity work.fa port map (a(2), b(2), c(2), fls(2), flc(2));
    ha: entity work.ha port map (d(0), fls(0), s(0), slc(0));
    csa3: entity work.fa port map (d(1), fls(1), flc(0), sls(0), slc(1));
    csa4: entity work.fa port map (d(2), fls(2), flc(1), sls(1), slc(2));
    rcai1 <= flc(2)&sls;
    rca: entity work.RippleCarryAdder port map(rcai1, slc, s(4 downto 1));
end architecture basic;

Tutorial/CarrySaveAdder_tb.vhdl
library ieee;
use ieee.std_logic_1164.all;
use ieee.numeric_std.all;

entity CarrySaveAdder_tb is
end CarrySaveAdder_tb;

architecture test of CarrySaveAdder_tb is
    signal a, b, c, d : std_logic_vector(2 downto 0);
    signal s : std_logic_vector(4 downto 0);
    signal avec, bvec, cvec, dvec : std_logic_vector(11 downto 0);
    signal abcd : std_logic_vector(11 downto 0);
    signal svec : std_logic_vector(11 downto 0);
begin
    CarrySaveAdder: entity work.CarrySaveAdder port map (a, b, c, d, s);
    process is
    begin

	for I in 0 to 4095 loop
	    abcd <= std_logic_vector(to_unsigned(I, abcd'length));
	    wait for 10 ns;
	    
	    a <= abcd(11 downto 9);
	    b <= abcd(8 downto 6);
	    c <= abcd(5 downto 3);
	    d <= abcd(2 downto 0);
	    wait for 10 ns;

            avec <= "000000000" & a;
            bvec <= "000000000" & b;
            cvec <= "000000000" & c;
            dvec <= "000000000" & d;
	    wait for 10 ns;

	    svec <= std_logic_vector(unsigned(avec) + unsigned(bvec) + unsigned(cvec) + unsigned(dvec));
	    wait for 10 ns;

	    if (svec(4) /= s(4)) or (svec(3) /= s(3)) or (svec(2) /= s(2)) or (svec(1) /= s(1)) or (svec(0) /= s(0)) then
		report "FAILURE";
	    --end if;
	        report "Input: " & std_logic'image(a(2)) & std_logic'image(a(1)) & std_logic'image(a(0)) & " " & std_logic'image(b(2)) & std_logic'image(b(1)) & std_logic'image(b(0)) & " " & std_logic'image(c(2)) & std_logic'image(c(1)) & std_logic'image(c(0)) & " " & std_logic'image(d(2)) & std_logic'image(d(1)) & std_logic'image(d(0));
	        report "Expected: " & std_logic'image(svec(4)) & std_logic'image(svec(3)) & std_logic'image(svec(2)) & std_logic'image(svec(1)) & std_logic'image(svec(0));
	        report "Got: " & std_logic'image(s(4)) & std_logic'image(s(3)) & std_logic'image(s(2)) & std_logic'image(s(1)) & std_logic'image(s(0));
            end if;
        end loop;
        wait;
    end process;
end architecture test;

Tutorial/CarrySaveAdder.vcd
$date
  Wed Jun 17 04:58:43 2020
$end
$version
  GHDL v0
$end
$timescale
  1 fs
$end
$scope module standard $end
$upscope $end
$scope module std_logic_1164 $end
$upscope $end
$scope module numeric_std $end
$upscope $end
$scope module carrysaveadder_tb $end
$var reg 3 ! a[2:0] $end
$var reg 3 " b[2:0] $end
$var reg 3 # c[2:0] $end
$var reg 3 $ d[2:0] $end
$var reg 5 % s[4:0] $end
$scope module carrysaveadder $end
$var reg 3 & a[2:0] $end
$var reg 3 ' b[2:0] $end
$var reg 3 ( c[2:0] $end
$var reg 3 ) d[2:0] $end
$var reg 5 * s[4:0] $end
$var reg 3 + fls[2:0] $end
$var reg 3 , flc[2:0] $end
$var reg 2 - sls[1:0] $end
$var reg 3 . slc[2:0] $end
$var reg 3 / rcai1[2:0] $end
$scope module csa0 $end
$var reg 1 0 a $end
$var reg 1 1 b $end
$var reg 1 2 ci $end
$var reg 1 3 s $end
$var reg 1 4 co $end
$var reg 1 5 s0 $end
$var reg 1 6 s1 $end
$var reg 1 7 c0 $end
$var reg 1 8 c1 $end
$scope module ha0 $end
$var reg 1 9 a $end
$var reg 1 : b $end
$var reg 1 ; s $end
$var reg 1 < c $end
$upscope $end
$scope module ha1 $end
$var reg 1 = a $end
$var reg 1 > b $end
$var reg 1 ? s $end
$var reg 1 @ c $end
$upscope $end
$upscope $end
$scope module csa1 $end
$var reg 1 A a $end
$var reg 1 B b $end
$var reg 1 C ci $end
$var reg 1 D s $end
$var reg 1 E co $end
$var reg 1 F s0 $end
$var reg 1 G s1 $end
$var reg 1 H c0 $end
$var reg 1 I c1 $end
$scope module ha0 $end
$var reg 1 J a $end
$var reg 1 K b $end
$var reg 1 L s $end
$var reg 1 M c $end
$upscope $end
$scope module ha1 $end
$var reg 1 N a $end
$var reg 1 O b $end
$var reg 1 P s $end
$var reg 1 Q c $end
$upscope $end
$upscope $end
$scope module csa2 $end
$var reg 1 R a $end
$var reg 1 S b $end
$var reg 1 T ci $end
$var reg 1 U s $end
$var reg 1 V co $end
$var reg 1 W s0 $end
$var reg 1 X s1 $end
$var reg 1 Y c0 $end
$var reg 1 Z c1 $end
$scope module ha0 $end
$var reg 1 [ a $end
$var reg 1 \ b $end
$var reg 1 ] s $end
$var reg 1 ^ c $end
$upscope $end
$scope module ha1 $end
$var reg 1 _ a $end
$var reg 1 ` b $end
$var reg 1 a s $end
$var reg 1 b c $end
$upscope $end
$upscope $end
$scope module ha $end
$var reg 1 c a $end
$var reg 1 d b $end
$var reg 1 e s $end
$var reg 1 f c $end
$upscope $end
$scope module csa3 $end
$var reg 1 g a $end
$var reg 1 h b $end
$var reg 1 i ci $end
$var reg 1 j s $end
$var reg 1 k co $end
$var reg 1 l s0 $end
$var reg 1 m s1 $end
$var reg 1 n c0 $end
$var reg 1 o c1 $end
$scope module ha0 $end
$var reg 1 p a $end
$var reg 1 q b $end
$var reg 1 r s $end
$var reg 1 s c $end
$upscope $end
$scope module ha1 $end
$var reg 1 t a $end
$var reg 1 u b $end
$var reg 1 v s $end
$var reg 1 w c $end
$upscope $end
$upscope $end
$scope module csa4 $end
$var reg 1 x a $end
$var reg 1 y b $end
$var reg 1 z ci $end
$var reg 1 { s $end
$var reg 1 | co $end
$var reg 1 } s0 $end
$var reg 1 !" s1 $end
$var reg 1 "" c0 $end
$var reg 1 #" c1 $end
$scope module ha0 $end
$var reg 1 $" a $end
$var reg 1 %" b $end
$var reg 1 &" s $end
$var reg 1 '" c $end
$upscope $end
$scope module ha1 $end
$var reg 1 (" a $end
$var reg 1 )" b $end
$var reg 1 *" s $end
$var reg 1 +" c $end
$upscope $end
$upscope $end
$scope module rca $end
$var reg 3 ," a[2:0] $end
$var reg 3 -" b[2:0] $end
$var reg 4 ." s[3:0] $end
$var reg 1 /" c0 $end
$var reg 1 0" c1 $end
$scope module ha $end
$var reg 1 1" a $end
$var reg 1 2" b $end
$var reg 1 3" s $end
$var reg 1 4" c $end
$upscope $end
$scope module fa0 $end
$var reg 1 5" a $end
$var reg 1 6" b $end
$var reg 1 7" ci $end
$var reg 1 8" s $end
$var reg 1 9" co $end
$var reg 1 :" s0 $end
$var reg 1 ;" s1 $end
$var reg 1 <" c0 $end
$var reg 1 =" c1 $end
$scope module ha0 $end
$var reg 1 >" a $end
$var reg 1 ?" b $end
$var reg 1 @" s $end
$var reg 1 A" c $end
$upscope $end
$scope module ha1 $end
$var reg 1 B" a $end
$var reg 1 C" b $end
$var reg 1 D" s $end
$var reg 1 E" c $end
$upscope $end
$upscope $end
$scope module fa1 $end
$var reg 1 F" a $end
$var reg 1 G" b $end
$var reg 1 H" ci $end
$var reg 1 I" s $end
$var reg 1 J" co $end
$var reg 1 K" s0 $end
$var reg 1 L" s1 $end
$var reg 1 M" c0 $end
$var reg 1 N" c1 $end
$scope module ha0 $end
$var reg 1 O" a $end
$var reg 1 P" b $end
$var reg 1 Q" s $end
$var reg 1 R" c $end
$upscope $end
$scope module ha1 $end
$var reg 1 S" a $end
$var reg 1 T" b $end
$var reg 1 U" s $end
$var reg 1 V" c $end
$upscope $end
$upscope $end
$upscope $end
$upscope $end
$upscope $end
$enddefinitions $end
#0
b000 !
b000 "
b000 #
b000 $
b00000 %
b000 &
b000 '
b000 (
b000 )
b00000 *
b000 +
b000 ,
b00 -
b000 .
b000 /
00
01
02
03
04
05
06
07
08
09
0:
0;
0<
0=
0>
0?
0@
0A
0B
0C
0D
0E
0F
0G
0H
0I
0J
0K
0L
0M
0N
0O
0P
0Q
0R
0S
0T
0U
0V
0W
0X
0Y
0Z
0[
0\
0]
0^
0_
0`
0a
0b
0c
0d
0e
0f
0g
0h
0i
0j
0k
0l
0m
0n
0o
0p
0q
0r
0s
0t
0u
0v
0w
0x
0y
0z
0{
0|
0}
0!"
0""
0#"
0$"
0%"
0&"
0'"
0("
0)"
0*"
0+"
b000 ,"
b000 -"
b0000 ."
0/"
00"
01"
02"
03"
04"
05"
06"
07"
08"
09"
0:"
0;"
0<"
0="
0>"
0?"
0@"
0A"
0B"
0C"
0D"
0E"
0F"
0G"
0H"
0I"
0J"
0K"
0L"
0M"
0N"
0O"
0P"
0Q"
0R"
0S"
0T"
0U"
0V"
#10000000
b001 $
b00001 %
b001 )
b00001 *
1c
1e
#20000000
b010 $
b00010 %
b010 )
b00010 *
b01 -
b001 /
0c
0e
1g
1j
1l
1m
1p
1r
1t
1v
b001 ,"
b0001 ."
11"
13"
#30000000
b011 $
b00011 %
b011 )
b00011 *
1c
1e
#40000000
b100 $
b00100 %
b100 )
b00100 *
b10 -
b010 /
0c
0e
0g
0j
0l
0m
0p
0r
0t
0v
1x
1{
1}
1!"
1$"
1&"
1("
1*"
b010 ,"
b0010 ."
01"
03"
15"
18"
1:"
1;"
1>"
1@"
1B"
1D"
#50000000
b101 $
b00101 %
b101 )
b00101 *
1c
1e
#60000000
b110 $
b00110 %
b110 )
b00110 *
b11 -
b011 /
0c
0e
1g
1j
1l
1m
1p
1r
1t
1v
b011 ,"
b0011 ."
11"
13"
#70000000
b111 $
b00111 %
b111 )
b00111 *
1c
1e
#80000000
b001 #
b000 $
b00001 %
b001 (
b000 )
b00001 *
b001 +
b00 -
b000 /
12
13
16
1>
1?
0c
1d
1e
0g
0j
0l
0m
0p
0r
0t
0v
0x
0{
0}
0!"
0$"
0&"
0("
0*"
b000 ,"
b0000 ."
01"
03"
05"
08"
0:"
0;"
0>"
0@"
0B"
0D"
#90000000
b001 $
b00010 %
b001 )
b00010 *
b001 .
1c
0e
1f
b001 -"
b0001 ."
12"
13"
#100000000
b010 $
b00011 %
b010 )
b00011 *
b01 -
b000 .
b001 /
0c
1e
0f
1g
1j
1l
1m
1p
1r
1t
1v
b001 ,"
b000 -"
b0001 ."
11"
02"
13"
#110000000
b011 $
b00100 %
b011 )
b00100 *
b001 .
1c
0e
1f
b001 -"
b0010 ."
1/"
12"
03"
14"
17"
18"
1;"
1C"
1D"
#120000000
b100 $
b00101 %
b100 )
b00101 *
b10 -
b000 .
b010 /
0c
1e
0f
0g
0j
0l
0m
0p
0r
0t
0v
1x
1{
1}
1!"
1$"
1&"
1("
1*"
b010 ,"
b000 -"
b0010 ."
0/"
01"
02"
03"
04"
15"
07"
18"
1:"
1;"
1>"
1@"
1B"
0C"
1D"
#130000000
b101 $
b00110 %
b101 )
b00110 *
b001 .
1c
0e
1f
b001 -"
b0011 ."
12"
13"
#140000000
b110 $
b00111 %
b110 )
b00111 *
b11 -
b000 .
b011 /
0c
1e
0f
1g
1j
1l
1m
1p
1r
1t
1v
b011 ,"
b000 -"
b0011 ."
11"
02"
13"
#150000000
b111 $
b01000 %
b111 )
b01000 *
b001 .
1c
0e
1f
b001 -"
b0100 ."
1/"
10"
12"
03"
14"
17"
08"
19"
0;"
1="
1C"
0D"
1E"
1H"
1I"
1L"
1T"
1U"
#160000000
b010 #
b000 $
b00010 %
b010 (
b000 )
b00010 *
b010 +
b01 -
b000 .
b001 /
02
03
06
0>
0?
1C
1D
1G
1O
1P
0c
0d
0e
0f
0g
1h
1j
1l
1m
0p
1q
1r
1t
1v
0x
0{
0}
0!"
0$"
0&"
0("
0*"
b001 ,"
b000 -"
b0001 ."
0/"
00"
11"
02"
13"
04"
05"
07"
08"
09"
0:"
0;"
0="
0>"
0@"
0B"
0C"
0D"
0E"
0H"
0I"
0L"
0T"
0U"
#170000000
b001 $
b00011 %
b001 )
b00011 *
1c
1e
#180000000
b010 $
b00100 %
b010 )
b00100 *
b00 -
b010 .
b000 /
0c
0e
1g
0j
1k
0l
0m
1n
1p
0r
1s
0t
0v
b000 ,"
b010 -"
b0010 ."
01"
03"
16"
18"
1:"
1;"
1?"
1@"
1B"
1D"
#190000000
b011 $
b00101 %
b011 )
b00101 *
1c
1e
#200000000
b100 $
b00110 %
b100 )
b00110 *
b11 -
b000 .
b011 /
0c
0e
0g
1j
0k
1l
1m
0n
0p
1r
0s
1t
1v
1x
1{
1}
1!"
1$"
1&"
1("
1*"
b011 ,"
b000 -"
b0011 ."
11"
13"
15"
06"
18"
1:"
1;"
1>"
0?"
1@"
1B"
1D"
#210000000
b101 $
b00111 %
b101 )
b00111 *
1c
1e
#220000000
b110 $
b01000 %
b110 )
b01000 *
b10 -
b010 .
b010 /
0c
0e
1g
0j
1k
0l
0m
1n
1p
0r
1s
0t
0v
b010 ,"
b010 -"
b0100 ."
10"
01"
03"
16"
08"
19"
0:"
0;"
1<"
1?"
0@"
1A"
0B"
0D"
1H"
1I"
1L"
1T"
1U"
#230000000
b111 $
b01001 %
b111 )
b01001 *
1c
1e
#240000000
b011 #
b000 $
b00011 %
b011 (
b000 )
b00011 *
b011 +
b01 -
b000 .
b001 /
12
13
16
1>
1?
0c
1d
1e
0g
1j
0k
1l
1m
0n
0p
1r
0s
1t
1v
0x
0{
0}
0!"
0$"
0&"
0("
0*"
b001 ,"
b000 -"
b0001 ."
00"
11"
13"
05"
06"
08"
09"
0:"
0;"
0<"
0>"
0?"
0@"
0A"
0B"
0D"
0H"
0I"
0L"
0T"
0U"
#250000000
b001 $
b00100 %
b001 )
b00100 *
b001 .
1c
0e
1f
b001 -"
b0010 ."
1/"
12"
03"
14"
17"
18"
1;"
1C"
1D"
#260000000
b010 $
b00101 %
b010 )
b00101 *
b00 -
b010 .
b000 /
0c
1e
0f
1g
0j
1k
0l
0m
1n
1p
0r
1s
0t
0v
b000 ,"
b010 -"
b0010 ."
0/"
01"
02"
03"
04"
16"
07"
18"
1:"
1;"
1?"
1@"
1B"
0C"
1D"
#270000000
b011 $
b00110 %
b011 )
b00110 *
b011 .
1c
0e
1f
b011 -"
b0011 ."
12"
13"
#280000000
b100 $
b00111 %
b100 )
b00111 *
b11 -
b000 .
b011 /
0c
1e
0f
0g
1j
0k
1l
1m
0n
0p
1r
0s
1t
1v
1x
1{
1}
1!"
1$"
1&"
1("
1*"
b011 ,"
b000 -"
b0011 ."
11"
02"
13"
15"
06"
18"
1:"
1;"
1>"
0?"
1@"
1B"
1D"
#290000000
b101 $
b01000 %
b101 )
b01000 *
b001 .
1c
0e
1f
b001 -"
b0100 ."
1/"
10"
12"
03"
14"
17"
08"
19"
0;"
1="
1C"
0D"
1E"
1H"
1I"
1L"
1T"
1U"
#300000000
b110 $
b01001 %
b110 )
b01001 *
b10 -
b010 .
b010 /
0c
1e
0f
1g
0j
1k
0l
0m
1n
1p
0r
1s
0t
0v
b010 ,"
b010 -"
b0100 ."
0/"
01"
02"
03"
04"
16"
07"
08"
0:"
0;"
1<"
0="
1?"
0@"
1A"
0B"
0C"
0D"
0E"
#310000000
b111 $
b01010 %
b111 )
b01010 *
b011 .
1c
0e
1f
b011 -"
b0101 ."
12"
13"
#320000000
b100 #
b000 $
b00100 %
b100 (
b000 )
b00100 *
b100 +
b10 -
b000 .
b010 /
02
03
06
0>
0?
0C
0D
0G
0O
0P
1T
1U
1X
1`
1a
0c
0d
0e
0f
0g
0h
0j
0k
0l
0m
0n
0p
0q
0r
0s
0t
0v
0x
1y
1{
1}
1!"
0$"
1%"
1&"
1("
1*"
b010 ,"
b000 -"
b0010 ."
00"
01"
02"
03"
15"
06"
18"
09"
1:"
1;"
0<"
1>"
0?"
1@"
0A"
1B"
1D"
0H"
0I"
0L"
0T"
0U"
#330000000
b001 $
b00101 %
b001 )
b00101 *
1c
1e
#340000000
b010 $
b00110 %
b010 )
b00110 *
b11 -
b011 /
0c
0e
1g
1j
1l
1m
1p
1r
1t
1v
b011 ,"
b0011 ."
11"
13"
#350000000
b011 $
b00111 %
b011 )
b00111 *
1c
1e
#360000000
b100 $
b01000 %
b100 )
b01000 *
b00 -
b100 .
b000 /
0c
0e
0g
0j
0l
0m
0p
0r
0t
0v
1x
0{
1|
0}
0!"
1""
1$"
0&"
1'"
0("
0*"
b000 ,"
b100 -"
b0100 ."
01"
03"
05"
08"
0:"
0;"
0>"
0@"
0B"
0D"
1G"
1I"
1K"
1L"
1P"
1Q"
1S"
1U"
#370000000
b101 $
b01001 %
b101 )
b01001 *
1c
1e
#380000000
b110 $
b01010 %
b110 )
b01010 *
b01 -
b001 /
0c
0e
1g
1j
1l
1m
1p
1r
1t
1v
b001 ,"
b0101 ."
11"
13"
#390000000
b111 $
b01011 %
b111 )
b01011 *
1c
1e
#400000000
b101 #
b000 $
b00101 %
b101 (
b000 )
b00101 *
b101 +
b10 -
b000 .
b010 /
12
13
16
1>
1?
0c
1d
1e
0g
0j
0l
0m
0p
0r
0t
0v
0x
1{
0|
1}
1!"
0""
0$"
1&"
0'"
1("
1*"
b010 ,"
b000 -"
b0010 ."
01"
03"
15"
18"
1:"
1;"
1>"
1@"
1B"
1D"
0G"
0I"
0K"
0L"
0P"
0Q"
0S"
0U"
#410000000
b001 $
b00110 %
b001 )
b00110 *
b001 .
1c
0e
1f
b001 -"
b0011 ."
12"
13"
#420000000
b010 $
b00111 %
b010 )
b00111 *
b11 -
b000 .
b011 /
0c
1e
0f
1g
1j
1l
1m
1p
1r
1t
1v
b011 ,"
b000 -"
b0011 ."
11"
02"
13"
#430000000
b011 $
b01000 %
b011 )
b01000 *
b001 .
1c
0e
1f
b001 -"
b0100 ."
1/"
10"
12"
03"
14"
17"
08"
19"
0;"
1="
1C"
0D"
1E"
1H"
1I"
1L"
1T"
1U"
#440000000
b100 $
b01001 %
b100 )
b01001 *
b00 -
b100 .
b000 /
0c
1e
0f
0g
0j
0l
0m
0p
0r
0t
0v
1x
0{
1|
0}
0!"
1""
1$"
0&"
1'"
0("
0*"
b000 ,"
b100 -"
b0100 ."
0/"
00"
01"
02"
03"
04"
05"
07"
08"
09"
0:"
0;"
0="
0>"
0@"
0B"
0C"
0D"
0E"
1G"
0H"
1I"
0J"
1K"
1L"
0N"
1P"
1Q"
1S"
0T"
1U"
0V"
#450000000
b101 $
b01010 %
b101 )
b01010 *
b101 .
1c
0e
1f
b101 -"
b0101 ."
12"
13"
#460000000
b110 $
b01011 %
b110 )
b01011 *
b01 -
b100 .
b001 /
0c
1e
0f
1g
1j
1l
1m
1p
1r
1t
1v
b001 ,"
b100 -"
b0101 ."
11"
02"
13"
#470000000
b111 $
b01100 %
b111 )
b01100 *
b101 .
1c
0e
1f
b101 -"
b0110 ."
1/"
12"
03"
14"
17"
18"
1;"
1C"
1D"
#480000000
b110 #
b000 $
b00110 %
b110 (
b000 )
b00110 *
b110 +
b11 -
b000 .
b011 /
02
03
06
0>
0?
1C
1D
1G
1O
1P
0c
0d
0e
0f
0g
1h
1j
1l
1m
0p
1q
1r
1t
1v
0x
1{
0|
1}
1!"
0""
0$"
1&"
0'"
1("
1*"
b011 ,"
b000 -"
b0011 ."
0/"
11"
02"
13"
04"
15"
07"
18"
1:"
1;"
1>"
1@"
1B"
0C"
1D"
0G"
0I"
0K"
0L"
0P"
0Q"
0S"
0U"
#490000000
b001 $
b00111 %
b001 )
b00111 *
1c
1e
#500000000
b010 $
b01000 %
b010 )
b01000 *
b10 -
b010 .
b010 /
0c
0e
1g
0j
1k
0l
0m
1n
1p
0r
1s
0t
0v
b010 ,"
b010 -"
b0100 ."
10"
01"
03"
16"
08"
19"
0:"
0;"
1<"
1?"
0@"
1A"
0B"
0D"
1H"
1I"
1L"
1T"
1U"
#510000000
b011 $
b01001 %
b011 )
b01001 *
1c
1e
#520000000
b100 $
b01010 %
b100 )
b01010 *
b01 -
b100 .
b001 /
0c
0e
0g
1j
0k
1l
1m
0n
0p
1r
0s
1t
1v
1x
0{
1|
0}
0!"
1""
1$"
0&"
1'"
0("
0*"
b001 ,"
b100 -"
b0101 ."
00"
11"
13"
05"
06"
08"
09"
0:"
0;"
0<"
0>"
0?"
0@"
0A"
0B"
0D"
1G"
0H"
1I"
0J"
1K"
1L"
0N"
1P"
1Q"
1S"
0T"
1U"
0V"
#530000000
b101 $
b01011 %
b101 )
b01011 *
1c
1e
#540000000
b110 $
b01100 %
b110 )
b01100 *
b00 -
b110 .
b000 /
0c
0e
1g
0j
1k
0l
0m
1n
1p
0r
1s
0t
0v
b000 ,"
b110 -"
b0110 ."
01"
03"
16"
18"
1:"
1;"
1?"
1@"
1B"
1D"
#550000000
b111 $
b01101 %
b111 )
b01101 *
1c
1e
#560000000
b111 #
b000 $
b00111 %
b111 (
b000 )
b00111 *
b111 +
b11 -
b000 .
b011 /
12
13
16
1>
1?
0c
1d
1e
0g
1j
0k
1l
1m
0n
0p
1r
0s
1t
1v
0x
1{
0|
1}
1!"
0""
0$"
1&"
0'"
1("
1*"
b011 ,"
b000 -"
b0011 ."
11"
13"
15"
06"
18"
1:"
1;"
1>"
0?"
1@"
1B"
1D"
0G"
0I"
0K"
0L"
0P"
0Q"
0S"
0U"
#570000000
b001 $
b01000 %
b001 )
b01000 *
b001 .
1c
0e
1f
b001 -"
b0100 ."
1/"
10"
12"
03"
14"
17"
08"
19"
0;"
1="
1C"
0D"
1E"
1H"
1I"
1L"
1T"
1U"
#580000000
b010 $
b01001 %
b010 )
b01001 *
b10 -
b010 .
b010 /
0c
1e
0f
1g
0j
1k
0l
0m
1n
1p
0r
1s
0t
0v
b010 ,"
b010 -"
b0100 ."
0/"
01"
02"
03"
04"
16"
07"
08"
0:"
0;"
1<"
0="
1?"
0@"
1A"
0B"
0C"
0D"
0E"
#590000000
b011 $
b01010 %
b011 )
b01010 *
b011 .
1c
0e
1f
b011 -"
b0101 ."
12"
13"
#600000000
b100 $
b01011 %
b100 )
b01011 *
b01 -
b100 .
b001 /
0c
1e
0f
0g
1j
0k
1l
1m
0n
0p
1r
0s
1t
1v
1x
0{
1|
0}
0!"
1""
1$"
0&"
1'"
0("
0*"
b001 ,"
b100 -"
b0101 ."
00"
11"
02"
13"
05"
06"
08"
09"
0:"
0;"
0<"
0>"
0?"
0@"
0A"
0B"
0D"
1G"
0H"
1I"
0J"
1K"
1L"
0N"
1P"
1Q"
1S"
0T"
1U"
0V"
#610000000
b101 $
b01100 %
b101 )
b01100 *
b101 .
1c
0e
1f
b101 -"
b0110 ."
1/"
12"
03"
14"
17"
18"
1;"
1C"
1D"
#620000000
b110 $
b01101 %
b110 )
b01101 *
b00 -
b110 .
b000 /
0c
1e
0f
1g
0j
1k
0l
0m
1n
1p
0r
1s
0t
0v
b000 ,"
b110 -"
b0110 ."
0/"
01"
02"
03"
04"
16"
07"
18"
1:"
1;"
1?"
1@"
1B"
0C"
1D"
#630000000
b111 $
b01110 %
b111 )
b01110 *
b111 .
1c
0e
1f
b111 -"
b0111 ."
12"
13"
#640000000
b001 "
b000 #
b000 $
b00001 %
b001 '
b000 (
b000 )
b00001 *
b001 +
b00 -
b000 .
b000 /
11
02
13
15
16
1:
1;
1=
0>
1?
0C
0D
0G
0O
0P
0T
0U
0X
0`
0a
0c
1d
1e
0f
0g
0h
0j
0k
0l
0m
0n
0p
0q
0r
0s
0t
0v
0x
0y
0{
0|
0}
0!"
0""
0$"
0%"
0&"
0'"
0("
0*"
b000 ,"
b000 -"
b0000 ."
01"
02"
03"
05"
06"
08"
0:"
0;"
0>"
0?"
0@"
0B"
0D"
0G"
0I"
0K"
0L"
0P"
0Q"
0S"
0U"
#650000000
b001 $
b00010 %
b001 )
b00010 *
b001 .
1c
0e
1f
b001 -"
b0001 ."
12"
13"
#660000000
b010 $
b00011 %
b010 )
b00011 *
b01 -
b000 .
b001 /
0c
1e
0f
1g
1j
1l
1m
1p
1r
1t
1v
b001 ,"
b000 -"
b0001 ."
11"
02"
13"
#670000000
b011 $
b00100 %
b011 )
b00100 *
b001 .
1c
0e
1f
b001 -"
b0010 ."
1/"
12"
03"
14"
17"
18"
1;"
1C"
1D"
#680000000
b100 $
b00101 %
b100 )
b00101 *
b10 -
b000 .
b010 /
0c
1e
0f
0g
0j
0l
0m
0p
0r
0t
0v
1x
1{
1}
1!"
1$"
1&"
1("
1*"
b010 ,"
b000 -"
b0010 ."
0/"
01"
02"
03"
04"
15"
07"
18"
1:"
1;"
1>"
1@"
1B"
0C"
1D"
#690000000
b101 $
b00110 %
b101 )
b00110 *
b001 .
1c
0e
1f
b001 -"
b0011 ."
12"
13"
#700000000
b110 $
b00111 %
b110 )
b00111 *
b11 -
b000 .
b011 /
0c
1e
0f
1g
1j
1l
1m
1p
1r
1t
1v
b011 ,"
b000 -"
b0011 ."
11"
02"
13"
#710000000
b111 $
b01000 %
b111 )
b01000 *
b001 .
1c
0e
1f
b001 -"
b0100 ."
1/"
10"
12"
03"
14"
17"
08"
19"
0;"
1="
1C"
0D"
1E"
1H"
1I"
1L"
1T"
1U"
#720000000
b001 #
b000 $
b00010 %
b001 (
b000 )
b00010 *
b000 +
b001 ,
b01 -
b000 .
b001 /
12
03
14
06
18
1>
0?
1@
0c
0d
0e
0f
0g
1i
1j
0l
1m
0p
0r
0t
1u
1v
0x
0{
0}
0!"
0$"
0&"
0("
0*"
b001 ,"
b000 -"
b0001 ."
0/"
00"
11"
02"
13"
04"
05"
07"
08"
09"
0:"
0;"
0="
0>"
0@"
0B"
0C"
0D"
0E"
0H"
0I"
0L"
0T"
0U"
#730000000
b001 $
b00011 %
b001 )
b00011 *
1c
1e
#740000000
b010 $
b00100 %
b010 )
b00100 *
b00 -
b010 .
b000 /
0c
0e
1g
0j
1k
1l
0m
1o
1p
1r
1t
0v
1w
b000 ,"
b010 -"
b0010 ."
01"
03"
16"
18"
1:"
1;"
1?"
1@"
1B"
1D"
#750000000
b011 $
b00101 %
b011 )
b00101 *
1c
1e
#760000000
b100 $
b00110 %
b100 )
b00110 *
b11 -
b000 .
b011 /
0c
0e
0g
1j
0k
0l
1m
0o
0p
0r
0t
1v
0w
1x
1{
1}
1!"
1$"
1&"
1("
1*"
b011 ,"
b000 -"
b0011 ."
11"
13"
15"
06"
18"
1:"
1;"
1>"
0?"
1@"
1B"
1D"
#770000000
b101 $
b00111 %
b101 )
b00111 *
1c
1e
#780000000
b110 $
b01000 %
b110 )
b01000 *
b10 -
b010 .
b010 /
0c
0e
1g
0j
1k
1l
0m
1o
1p
1r
1t
0v
1w
b010 ,"
b010 -"
b0100 ."
10"
01"
03"
16"
08"
19"
0:"
0;"
1<"
1?"
0@"
1A"
0B"
0D"
1H"
1I"
1L"
1T"
1U"
#790000000
b111 $
b01001 %
b111 )
b01001 *
1c
1e
#800000000
b010 #
b000 $
b00011 %
b010 (
b000 )
b00011 *
b011 +
b000 ,
b01 -
b000 .
b001 /
02
13
04
16
08
0>
1?
0@
1C
1D
1G
1O
1P
0c
1d
1e
0g
1h
0i
1j
0k
1l
1m
0o
0p
1q
1r
1t
0u
1v
0w
0x
0{
0}
0!"
0$"
0&"
0("
0*"
b001 ,"
b000 -"
b0001 ."
00"
11"
13"
05"
06"
08"
09"
0:"
0;"
0<"
0>"
0?"
0@"
0A"
0B"
0D"
0H"
0I"
0L"
0T"
0U"
#810000000
b001 $
b00100 %
b001 )
b00100 *
b001 .
1c
0e
1f
b001 -"
b0010 ."
1/"
12"
03"
14"
17"
18"
1;"
1C"
1D"
#820000000
b010 $
b00101 %
b010 )
b00101 *
b00 -
b010 .
b000 /
0c
1e
0f
1g
0j
1k
0l
0m
1n
1p
0r
1s
0t
0v
b000 ,"
b010 -"
b0010 ."
0/"
01"
02"
03"
04"
16"
07"
18"
1:"
1;"
1?"
1@"
1B"
0C"
1D"
#830000000
b011 $
b00110 %
b011 )
b00110 *
b011 .
1c
0e
1f
b011 -"
b0011 ."
12"
13"
