Tutorial/ha.vhdl
library ieee;
use ieee.std_logic_1164.all;

entity ha is
    port (a, b : in std_logic; s, c : out std_logic);
end ha;

architecture basic of ha is
begin
    s <= a xor b;
    c <= a and b;
end architecture basic;

Tutorial/fa.vhdl
library ieee;
use ieee.std_logic_1164.all;

entity fa is
    port (a, b, ci : in std_logic; s, co : out std_logic);
end fa;

architecture basic of fa is
    signal s0, s1, c0, c1 : std_logic; -- temps for connecting outputs to inputs
begin
    ha0: entity work.ha port map (a, b, s0, c0);
    ha1: entity work.ha port map (s0, ci, s1, c1);
    s <= s1;
    co <= c0 or c1;
end architecture basic;

Tutorial/RippleCarryAdder.vhdl
library ieee;
use ieee.std_logic_1164.all;

entity RippleCarryAdder is
    port (a, b : in std_logic_vector(2 downto 0); s : out std_logic_vector(3 downto 0));
end RippleCarryAdder;

architecture basic of RippleCarryAdder is
signal c0, c1 : std_logic;
begin
    ha: entity work.ha port map(a(0), b(0), s(0), c0);
    fa0: entity work.fa port map (a(1), b(1), c0, s(1), c1);
    fa1: entity work.fa port map (a(2), b(2), c1, s(2), s(3));
end architecture basic;

Tutorial/RippleCarryAdder_tb.vhdl
library ieee;
use ieee.std_logic_1164.all;
use ieee.numeric_std.all;

entity RippleCarryAdder_tb is
end RippleCarryAdder_tb;

architecture test of RippleCarryAdder_tb is
    signal a, b : std_logic_vector(2 downto 0);
    signal s : std_logic_vector(3 downto 0);
    signal avec, bvec : std_logic_vector(5 downto 0);
    signal ab : std_logic_vector(5 downto 0);
    signal svec : std_logic_vector(5 downto 0);
begin
    RippleCarryAdder: entity work.RippleCarryAdder port map (a, b, s);
    process is
    begin
	
	for I in 0 to 63 loop
	    ab <= std_logic_vector(to_unsigned(I, ab'length));
	    wait for 10 ns;
	    
	    a <= ab(5 downto 3);
	    b <= ab(2 downto 0);
	    wait for 10 ns;

	    avec <= "000" & a;
	    bvec <= "000" & b;
	    wait for 10 ns;
            
	    svec <= std_logic_vector(unsigned(avec) + unsigned(bvec));
	    wait for 10 ns;
	    
	    if (svec(3) /= s(3)) or (svec(2) /= s(2)) or (svec(1) /= s(1)) or (svec(0) /= s(0)) then
		report "FAILURE";
	    --end if;
	        report "Input: " & std_logic'image(a(2)) & std_logic'image(a(1)) & std_logic'image(a(0)) & " " & std_logic'image(b(2)) & std_logic'image(b(1)) & std_logic'image(b(0));
	        report "Expected: " & std_logic'image(svec(5)) & std_logic'image(svec(4)) & std_logic'image(svec(3)) & std_logic'image(svec(2)) & std_logic'image(svec(1)) & std_logic'image(svec(0));
	        report "Got: " & std_logic'image(s(3)) & std_logic'image(s(2)) & std_logic'image(s(1)) & std_logic'image(s(0));
                report "";
	    end if;
        end loop;
	
        wait;
    end process;
end architecture test;

Tutorial/RippleCarryAdder.vcd
$date
  Wed Jun 17 04:11:46 2020
$end
$version
  GHDL v0
$end
$timescale
  1 fs
$end
$scope module standard $end
$upscope $end
$scope module std_logic_1164 $end
$upscope $end
$scope module numeric_std $end
$upscope $end
$scope module ripplecarryadder_tb $end
$var reg 3 ! a[2:0] $end
$var reg 3 " b[2:0] $end
$var reg 4 # s[3:0] $end
$scope module ripplecarryadder $end
$var reg 3 $ a[2:0] $end
$var reg 3 % b[2:0] $end
$var reg 4 & s[3:0] $end
$var reg 1 ' c0 $end
$var reg 1 ( c1 $end
$scope module ha $end
$var reg 1 ) a $end
$var reg 1 * b $end
$var reg 1 + s $end
$var reg 1 , c $end
$upscope $end
$scope module fa0 $end
$var reg 1 - a $end
$var reg 1 . b $end
$var reg 1 / ci $end
$var reg 1 0 s $end
$var reg 1 1 co $end
$var reg 1 2 s0 $end
$var reg 1 3 s1 $end
$var reg 1 4 c0 $end
$var reg 1 5 c1 $end
$scope module ha0 $end
$var reg 1 6 a $end
$var reg 1 7 b $end
$var reg 1 8 s $end
$var reg 1 9 c $end
$upscope $end
$scope module ha1 $end
$var reg 1 : a $end
$var reg 1 ; b $end
$var reg 1 < s $end
$var reg 1 = c $end
$upscope $end
$upscope $end
$scope module fa1 $end
$var reg 1 > a $end
$var reg 1 ? b $end
$var reg 1 @ ci $end
$var reg 1 A s $end
$var reg 1 B co $end
$var reg 1 C s0 $end
$var reg 1 D s1 $end
$var reg 1 E c0 $end
$var reg 1 F c1 $end
$scope module ha0 $end
$var reg 1 G a $end
$var reg 1 H b $end
$var reg 1 I s $end
$var reg 1 J c $end
$upscope $end
$scope module ha1 $end
$var reg 1 K a $end
$var reg 1 L b $end
$var reg 1 M s $end
$var reg 1 N c $end
$upscope $end
$upscope $end
$upscope $end
$upscope $end
$enddefinitions $end
#0
b000 !
b000 "
b0000 #
b000 $
b000 %
b0000 &
0'
0(
0)
0*
0+
0,
0-
0.
0/
00
01
02
03
04
05
06
07
08
09
0:
0;
0<
0=
0>
0?
0@
0A
0B
0C
0D
0E
0F
0G
0H
0I
0J
0K
0L
0M
0N
#10000000
b001 "
b0001 #
b001 %
b0001 &
1*
1+
#20000000
b010 "
b0010 #
b010 %
b0010 &
0*
0+
1.
10
12
13
17
18
1:
1<
#30000000
b011 "
b0011 #
b011 %
b0011 &
1*
1+
#40000000
b100 "
b0100 #
b100 %
b0100 &
0*
0+
0.
00
02
03
07
08
0:
0<
1?
1A
1C
1D
1H
1I
1K
1M
#50000000
b101 "
b0101 #
b101 %
b0101 &
1*
1+
#60000000
b110 "
b0110 #
b110 %
b0110 &
0*
0+
1.
10
12
13
17
18
1:
1<
#70000000
b111 "
b0111 #
b111 %
b0111 &
1*
1+
#80000000
b001 !
b000 "
b0001 #
b001 $
b000 %
b0001 &
1)
0*
0.
00
02
03
07
08
0:
0<
0?
0A
0C
0D
0H
0I
0K
0M
#90000000
b001 "
b0010 #
b001 %
b0010 &
1'
1*
0+
1,
1/
10
13
1;
1<
#100000000
b010 "
b0011 #
b010 %
b0011 &
0'
0*
1+
0,
1.
0/
12
17
18
1:
0;
#110000000
b011 "
b0100 #
b011 %
b0100 &
1'
1(
1*
0+
1,
1/
00
11
03
15
1;
0<
1=
1@
1A
1D
1L
1M
#120000000
b100 "
b0101 #
b100 %
b0101 &
0'
0(
0*
1+
0,
0.
0/
01
02
05
07
08
0:
0;
0=
1?
0@
1A
0B
1C
1D
0F
1H
1I
1K
0L
1M
0N
#130000000
b101 "
b0110 #
b101 %
b0110 &
1'
1*
0+
1,
1/
10
13
1;
1<
#140000000
b110 "
b0111 #
b110 %
b0111 &
0'
0*
1+
0,
1.
0/
12
17
18
1:
0;
#150000000
b111 "
b1000 #
b111 %
b1000 &
1'
1(
1*
0+
1,
1/
00
11
03
15
1;
0<
1=
1@
0A
1B
0D
1F
1L
0M
1N
#160000000
b010 !
b000 "
b0010 #
b010 $
b000 %
b0010 &
0'
0(
0)
0*
0,
1-
0.
0/
10
01
13
05
16
07
0;
1<
0=
0?
0@
0A
0B
0C
0D
0F
0H
0I
0K
0L
0M
0N
#170000000
b001 "
b0011 #
b001 %
b0011 &
1*
1+
#180000000
b010 "
b0100 #
b010 %
b0100 &
1(
0*
0+
1.
00
11
02
03
14
17
08
19
0:
0<
1@
1A
1D
1L
1M
#190000000
b011 "
b0101 #
b011 %
b0101 &
1*
1+
#200000000
b100 "
b0110 #
b100 %
b0110 &
0(
0*
0+
0.
10
01
12
13
04
07
18
09
1:
1<
1?
0@
1A
0B
1C
1D
0F
1H
1I
1K
0L
1M
0N
#210000000
b101 "
b0111 #
b101 %
b0111 &
1*
1+
#220000000
b110 "
b1000 #
b110 %
b1000 &
1(
0*
0+
1.
00
11
02
03
14
17
08
19
0:
0<
1@
0A
1B
0D
1F
1L
0M
1N
#230000000
b111 "
b1001 #
b111 %
b1001 &
1*
1+
#240000000
b011 !
b000 "
b0011 #
b011 $
b000 %
b0011 &
0(
1)
0*
0.
10
01
12
13
04
07
18
09
1:
1<
0?
0@
0A
0B
0C
0D
0F
0H
0I
0K
0L
0M
0N
#250000000
b001 "
b0100 #
b001 %
b0100 &
1'
1(
1*
0+
1,
1/
00
11
03
15
1;
0<
1=
1@
1A
1D
1L
1M
#260000000
b010 "
b0101 #
b010 %
b0101 &
0'
0*
1+
0,
1.
0/
02
14
05
17
08
19
0:
0;
0=
#270000000
b011 "
b0110 #
b011 %
b0110 &
1'
1*
0+
1,
1/
10
13
1;
1<
#280000000
b100 "
b0111 #
b100 %
b0111 &
0'
0(
0*
1+
0,
0.
0/
01
12
04
07
18
09
1:
0;
1?
0@
1A
0B
1C
1D
0F
1H
1I
1K
0L
1M
0N
#290000000
b101 "
b1000 #
b101 %
b1000 &
1'
1(
1*
0+
1,
1/
00
11
03
15
1;
0<
1=
1@
0A
1B
0D
1F
1L
0M
1N
#300000000
b110 "
b1001 #
b110 %
b1001 &
0'
0*
1+
0,
1.
0/
02
14
05
17
08
19
0:
0;
0=
#310000000
b111 "
b1010 #
b111 %
b1010 &
1'
1*
0+
1,
1/
10
13
1;
1<
#320000000
b100 !
b000 "
b0100 #
b100 $
b000 %
b0100 &
0'
0(
0)
0*
0,
0-
0.
0/
00
01
03
04
06
07
09
0;
0<
1>
0?
0@
1A
0B
1D
0F
1G
0H
0L
1M
0N
#330000000
b001 "
b0101 #
b001 %
b0101 &
1*
1+
#340000000
b010 "
b0110 #
b010 %
b0110 &
0*
0+
1.
10
12
13
17
18
1:
1<
#350000000
b011 "
b0111 #
b011 %
b0111 &
1*
1+
#360000000
b100 "
b1000 #
b100 %
b1000 &
0*
0+
0.
00
02
03
07
08
0:
0<
1?
0A
1B
0C
0D
1E
1H
0I
1J
0K
0M
#370000000
b101 "
b1001 #
b101 %
b1001 &
1*
1+
#380000000
b110 "
b1010 #
b110 %
b1010 &
0*
0+
1.
10
12
13
17
18
1:
1<
#390000000
b111 "
b1011 #
b111 %
b1011 &
1*
1+
#400000000
b101 !
b000 "
b0101 #
b101 $
b000 %
b0101 &
1)
0*
0.
00
02
03
07
08
0:
0<
0?
1A
0B
1C
1D
0E
0H
1I
0J
1K
1M
#410000000
b001 "
b0110 #
b001 %
b0110 &
1'
1*
0+
1,
1/
10
13
1;
1<
#420000000
b010 "
b0111 #
b010 %
b0111 &
0'
0*
1+
0,
1.
0/
12
17
18
1:
0;
#430000000
b011 "
b1000 #
b011 %
b1000 &
1'
1(
1*
0+
1,
1/
00
11
03
15
1;
0<
1=
1@
0A
1B
0D
1F
1L
0M
1N
#440000000
b100 "
b1001 #
b100 %
b1001 &
0'
0(
0*
1+
0,
0.
0/
01
02
05
07
08
0:
0;
0=
1?
0@
0A
0C
0D
1E
0F
1H
0I
1J
0K
0L
0M
0N
#450000000
b101 "
b1010 #
b101 %
b1010 &
1'
1*
0+
1,
1/
10
13
1;
1<
#460000000
b110 "
b1011 #
b110 %
b1011 &
0'
0*
1+
0,
1.
0/
12
17
18
1:
0;
#470000000
b111 "
b1100 #
b111 %
b1100 &
1'
1(
1*
0+
1,
1/
00
11
03
15
1;
0<
1=
1@
1A
1D
1L
1M
#480000000
b110 !
b000 "
b0110 #
b110 $
b000 %
b0110 &
0'
0(
0)
0*
0,
1-
0.
0/
10
01
13
05
16
07
0;
1<
0=
0?
0@
1A
0B
1C
1D
0E
0F
0H
1I
0J
1K
0L
1M
0N
#490000000
b001 "
b0111 #
b001 %
b0111 &
1*
1+
#500000000
b010 "
b1000 #
b010 %
b1000 &
1(
0*
0+
1.
00
11
02
03
14
17
08
19
0:
0<
1@
0A
1B
0D
1F
1L
0M
1N
#510000000
b011 "
b1001 #
b011 %
b1001 &
1*
1+
#520000000
b100 "
b1010 #
b100 %
b1010 &
0(
0*
0+
0.
10
01
12
13
04
07
18
09
1:
1<
1?
0@
0A
0C
0D
1E
0F
1H
0I
1J
0K
0L
0M
0N
#530000000
b101 "
b1011 #
b101 %
b1011 &
1*
1+
#540000000
b110 "
b1100 #
b110 %
b1100 &
1(
0*
0+
1.
00
11
02
03
14
17
08
19
0:
0<
1@
1A
1D
1L
1M
#550000000
b111 "
b1101 #
b111 %
b1101 &
1*
1+
#560000000
b111 !
b000 "
b0111 #
b111 $
b000 %
b0111 &
0(
1)
0*
0.
10
01
12
13
04
07
18
09
1:
1<
0?
0@
1A
0B
1C
1D
0E
0F
0H
1I
0J
1K
0L
1M
0N
#570000000
b001 "
b1000 #
b001 %
b1000 &
1'
1(
1*
0+
1,
1/
00
11
03
15
1;
0<
1=
1@
0A
1B
0D
1F
1L
0M
1N
#580000000
b010 "
b1001 #
b010 %
b1001 &
0'
0*
1+
0,
1.
0/
02
14
05
17
08
19
0:
0;
0=
#590000000
b011 "
b1010 #
b011 %
b1010 &
1'
1*
0+
1,
1/
10
13
1;
1<
#600000000
b100 "
b1011 #
b100 %
b1011 &
0'
0(
0*
1+
0,
0.
0/
01
12
04
07
18
09
1:
0;
1?
0@
0A
0C
0D
1E
0F
1H
0I
1J
0K
0L
0M
0N
#610000000
b101 "
b1100 #
b101 %
b1100 &
1'
1(
1*
0+
1,
1/
00
11
03
15
1;
0<
1=
1@
1A
1D
1L
1M
#620000000
b110 "
b1101 #
b110 %
b1101 &
0'
0*
1+
0,
1.
0/
02
14
05
17
08
19
0:
0;
0=
#630000000
b111 "
b1110 #
b111 %
b1110 &
1'
1*
0+
1,
1/
10
13
1;
1<
